localpass/__init__.py
localpass/__main__.py
localpass/cli.py
localpass/hibp.py
localpass/prompts.py
localpass/version.py
localpass/vault/__init__.py
localpass/vault/crypto.py
localpass/vault/models.py
localpass/vault/repository.py
localpass/vault/service.py
localpass/vault/vault_serialization.py
localpass-0.3.0.dist-info/METADATA
localpass-0.3.0.dist-info/WHEEL
localpass-0.3.0.dist-info/entry_points.txt
localpass-0.3.0.dist-info/licenses/LICENSE
localpass-0.3.0.dist-info/RECORD
