Metadata-Version: 2.4
Name: localpass
Version: 0.3.0
Summary: Local-first, offline password manager.
Author: Łukasz Perek, lukasz.perek@outlook.com
License: Apache-2.0
License-File: LICENSE
Requires-Python: >=3.11
Requires-Dist: click>=8.0
Requires-Dist: cryptography
Requires-Dist: requests
Requires-Dist: zxcvbn
Provides-Extra: dev
Requires-Dist: black; extra == 'dev'
Requires-Dist: mypy; extra == 'dev'
Requires-Dist: pytest; extra == 'dev'
Requires-Dist: pytest-cov; extra == 'dev'
Requires-Dist: ruff; extra == 'dev'
